MANIFEST.in
README.md
setup.py
libpythonproRhm/__init__.py
libpythonproRhm/github_api.py
libpythonproRhm.egg-info/PKG-INFO
libpythonproRhm.egg-info/SOURCES.txt
libpythonproRhm.egg-info/dependency_links.txt
libpythonproRhm.egg-info/not-zip-safe
libpythonproRhm.egg-info/requires.txt
libpythonproRhm.egg-info/top_level.txt